{
  "openapi": "3.1.0",
  "info": {
    "title": "OmniLab",
    "version": "1.0.0"
  },
  "paths": {
    "/api/license/status": {
      "get": {
        "tags": [
          "license"
        ],
        "summary": "Get License Status",
        "description": "Get current license info.",
        "operationId": "get_license_status_api_license_status_get",
        "responses": {
          "200": {
            "description": "Successful Response",
            "content": {
              "application/json": {
                "schema": {}
              }
            }
          }
        }
      }
    },
    "/api/license/activate": {
      "post": {
        "tags": [
          "license"
        ],
        "summary": "Activate License",
        "description": "Activate a license key.",
        "operationId": "activate_license_api_license_activate_post",
        "requestBody": {
          "content": {
            "application/json": {
              "schema": {
                "$ref": "#/components/schemas/LicenseActivate"
              }
            }
          },
          "required": true
        },
        "responses": {
          "200": {
            "description": "Successful Response",
            "content": {
              "application/json": {
                "schema": {}
              }
            }
          },
          "422": {
            "description": "Validation Error",
            "content": {
              "application/json": {
                "schema": {
                  "$ref": "#/components/schemas/HTTPValidationError"
                }
              }
            }
          }
        }
      }
    },
    "/api/license/deactivate": {
      "post": {
        "tags": [
          "license"
        ],
        "summary": "Deactivate License",
        "description": "Remove the activated license (revert to free tier).",
        "operationId": "deactivate_license_api_license_deactivate_post",
        "responses": {
          "200": {
            "description": "Successful Response",
            "content": {
              "application/json": {
                "schema": {}
              }
            }
          }
        }
      }
    },
    "/api/license/generate": {
      "post": {
        "tags": [
          "license"
        ],
        "summary": "Generate License Key",
        "description": "Generate a new license key.\nIn production, this endpoint should be removed or require admin auth.\nFor now, useful for testing.",
        "operationId": "generate_license_key_api_license_generate_post",
        "parameters": [
          {
            "name": "plan",
            "in": "query",
            "required": false,
            "schema": {
              "type": "string",
              "default": "pro",
              "title": "Plan"
            }
          },
          {
            "name": "customer",
            "in": "query",
            "required": false,
            "schema": {
              "type": "string",
              "default": "user",
              "title": "Customer"
            }
          }
        ],
        "responses": {
          "200": {
            "description": "Successful Response",
            "content": {
              "application/json": {
                "schema": {}
              }
            }
          },
          "422": {
            "description": "Validation Error",
            "content": {
              "application/json": {
                "schema": {
                  "$ref": "#/components/schemas/HTTPValidationError"
                }
              }
            }
          }
        }
      }
    },
    "/api/billing/health": {
      "get": {
        "tags": [
          "billing"
        ],
        "summary": "Billing Health",
        "operationId": "billing_health_api_billing_health_get",
        "responses": {
          "200": {
            "description": "Successful Response",
            "content": {
              "application/json": {
                "schema": {}
              }
            }
          }
        }
      }
    },
    "/api/billing/create-checkout-session": {
      "post": {
        "tags": [
          "billing"
        ],
        "summary": "Create Checkout Session",
        "operationId": "create_checkout_session_api_billing_create_checkout_session_post",
        "requestBody": {
          "content": {
            "application/json": {
              "schema": {
                "$ref": "#/components/schemas/CheckoutSessionRequest"
              }
            }
          },
          "required": true
        },
        "responses": {
          "200": {
            "description": "Successful Response",
            "content": {
              "application/json": {
                "schema": {}
              }
            }
          },
          "422": {
            "description": "Validation Error",
            "content": {
              "application/json": {
                "schema": {
                  "$ref": "#/components/schemas/HTTPValidationError"
                }
              }
            }
          }
        }
      }
    },
    "/api/billing/webhook": {
      "post": {
        "tags": [
          "billing"
        ],
        "summary": "Stripe Webhook",
        "operationId": "stripe_webhook_api_billing_webhook_post",
        "responses": {
          "200": {
            "description": "Successful Response",
            "content": {
              "application/json": {
                "schema": {}
              }
            }
          }
        }
      }
    },
    "/api/labs/": {
      "get": {
        "summary": "List Labs",
        "operationId": "list_labs_api_labs__get",
        "responses": {
          "200": {
            "description": "Successful Response",
            "content": {
              "application/json": {
                "schema": {}
              }
            }
          }
        }
      },
      "post": {
        "summary": "Create Lab",
        "operationId": "create_lab_api_labs__post",
        "requestBody": {
          "content": {
            "application/json": {
              "schema": {
                "$ref": "#/components/schemas/LabCreate"
              }
            }
          },
          "required": true
        },
        "responses": {
          "201": {
            "description": "Successful Response",
            "content": {
              "application/json": {
                "schema": {}
              }
            }
          },
          "422": {
            "description": "Validation Error",
            "content": {
              "application/json": {
                "schema": {
                  "$ref": "#/components/schemas/HTTPValidationError"
                }
              }
            }
          }
        }
      }
    },
    "/api/labs/{lab_id}": {
      "get": {
        "summary": "Get Lab",
        "operationId": "get_lab_api_labs__lab_id__get",
        "parameters": [
          {
            "name": "lab_id",
            "in": "path",
            "required": true,
            "schema": {
              "type": "string",
              "title": "Lab Id"
            }
          }
        ],
        "responses": {
          "200": {
            "description": "Successful Response",
            "content": {
              "application/json": {
                "schema": {}
              }
            }
          },
          "422": {
            "description": "Validation Error",
            "content": {
              "application/json": {
                "schema": {
                  "$ref": "#/components/schemas/HTTPValidationError"
                }
              }
            }
          }
        }
      },
      "delete": {
        "summary": "Delete Lab",
        "operationId": "delete_lab_api_labs__lab_id__delete",
        "parameters": [
          {
            "name": "lab_id",
            "in": "path",
            "required": true,
            "schema": {
              "type": "string",
              "title": "Lab Id"
            }
          }
        ],
        "responses": {
          "204": {
            "description": "Successful Response"
          },
          "422": {
            "description": "Validation Error",
            "content": {
              "application/json": {
                "schema": {
                  "$ref": "#/components/schemas/HTTPValidationError"
                }
              }
            }
          }
        }
      }
    },
    "/api/labs/{lab_id}/topology": {
      "get": {
        "summary": "Get Topology",
        "operationId": "get_topology_api_labs__lab_id__topology_get",
        "parameters": [
          {
            "name": "lab_id",
            "in": "path",
            "required": true,
            "schema": {
              "type": "string",
              "title": "Lab Id"
            }
          }
        ],
        "responses": {
          "200": {
            "description": "Successful Response",
            "content": {
              "application/json": {
                "schema": {}
              }
            }
          },
          "422": {
            "description": "Validation Error",
            "content": {
              "application/json": {
                "schema": {
                  "$ref": "#/components/schemas/HTTPValidationError"
                }
              }
            }
          }
        }
      }
    },
    "/api/labs/{lab_id}/export": {
      "get": {
        "summary": "Export Lab",
        "operationId": "export_lab_api_labs__lab_id__export_get",
        "parameters": [
          {
            "name": "lab_id",
            "in": "path",
            "required": true,
            "schema": {
              "type": "string",
              "title": "Lab Id"
            }
          }
        ],
        "responses": {
          "200": {
            "description": "Successful Response",
            "content": {
              "application/json": {
                "schema": {}
              }
            }
          },
          "422": {
            "description": "Validation Error",
            "content": {
              "application/json": {
                "schema": {
                  "$ref": "#/components/schemas/HTTPValidationError"
                }
              }
            }
          }
        }
      }
    },
    "/api/labs/import": {
      "post": {
        "summary": "Import Lab",
        "operationId": "import_lab_api_labs_import_post",
        "requestBody": {
          "content": {
            "application/json": {
              "schema": {
                "$ref": "#/components/schemas/ImportPayload"
              }
            }
          },
          "required": true
        },
        "responses": {
          "201": {
            "description": "Successful Response",
            "content": {
              "application/json": {
                "schema": {}
              }
            }
          },
          "422": {
            "description": "Validation Error",
            "content": {
              "application/json": {
                "schema": {
                  "$ref": "#/components/schemas/HTTPValidationError"
                }
              }
            }
          }
        }
      }
    },
    "/api/nodes/": {
      "post": {
        "summary": "Add Node",
        "operationId": "add_node_api_nodes__post",
        "requestBody": {
          "content": {
            "application/json": {
              "schema": {
                "$ref": "#/components/schemas/NodeCreate"
              }
            }
          },
          "required": true
        },
        "responses": {
          "201": {
            "description": "Successful Response",
            "content": {
              "application/json": {
                "schema": {}
              }
            }
          },
          "422": {
            "description": "Validation Error",
            "content": {
              "application/json": {
                "schema": {
                  "$ref": "#/components/schemas/HTTPValidationError"
                }
              }
            }
          }
        }
      }
    },
    "/api/nodes/{node_id}": {
      "get": {
        "summary": "Get Node",
        "operationId": "get_node_api_nodes__node_id__get",
        "parameters": [
          {
            "name": "node_id",
            "in": "path",
            "required": true,
            "schema": {
              "type": "string",
              "title": "Node Id"
            }
          }
        ],
        "responses": {
          "200": {
            "description": "Successful Response",
            "content": {
              "application/json": {
                "schema": {}
              }
            }
          },
          "422": {
            "description": "Validation Error",
            "content": {
              "application/json": {
                "schema": {
                  "$ref": "#/components/schemas/HTTPValidationError"
                }
              }
            }
          }
        }
      },
      "delete": {
        "summary": "Delete Node",
        "operationId": "delete_node_api_nodes__node_id__delete",
        "parameters": [
          {
            "name": "node_id",
            "in": "path",
            "required": true,
            "schema": {
              "type": "string",
              "title": "Node Id"
            }
          }
        ],
        "responses": {
          "204": {
            "description": "Successful Response"
          },
          "422": {
            "description": "Validation Error",
            "content": {
              "application/json": {
                "schema": {
                  "$ref": "#/components/schemas/HTTPValidationError"
                }
              }
            }
          }
        }
      },
      "patch": {
        "summary": "Update Node",
        "description": "Update node fields: name, config (startup config), x, y position.",
        "operationId": "update_node_api_nodes__node_id__patch",
        "parameters": [
          {
            "name": "node_id",
            "in": "path",
            "required": true,
            "schema": {
              "type": "string",
              "title": "Node Id"
            }
          }
        ],
        "requestBody": {
          "required": true,
          "content": {
            "application/json": {
              "schema": {
                "$ref": "#/components/schemas/NodeUpdate"
              }
            }
          }
        },
        "responses": {
          "200": {
            "description": "Successful Response",
            "content": {
              "application/json": {
                "schema": {}
              }
            }
          },
          "422": {
            "description": "Validation Error",
            "content": {
              "application/json": {
                "schema": {
                  "$ref": "#/components/schemas/HTTPValidationError"
                }
              }
            }
          }
        }
      }
    },
    "/api/nodes/{node_id}/start": {
      "post": {
        "summary": "Start Node",
        "description": "Start a node. For VNC nodes, spawns QEMU and assigns a VNC port.",
        "operationId": "start_node_api_nodes__node_id__start_post",
        "parameters": [
          {
            "name": "node_id",
            "in": "path",
            "required": true,
            "schema": {
              "type": "string",
              "title": "Node Id"
            }
          }
        ],
        "responses": {
          "200": {
            "description": "Successful Response",
            "content": {
              "application/json": {
                "schema": {}
              }
            }
          },
          "422": {
            "description": "Validation Error",
            "content": {
              "application/json": {
                "schema": {
                  "$ref": "#/components/schemas/HTTPValidationError"
                }
              }
            }
          }
        }
      }
    },
    "/api/nodes/{node_id}/stop": {
      "post": {
        "summary": "Stop Node",
        "description": "Stop a node. For VNC nodes, kills the QEMU process.",
        "operationId": "stop_node_api_nodes__node_id__stop_post",
        "parameters": [
          {
            "name": "node_id",
            "in": "path",
            "required": true,
            "schema": {
              "type": "string",
              "title": "Node Id"
            }
          }
        ],
        "responses": {
          "200": {
            "description": "Successful Response",
            "content": {
              "application/json": {
                "schema": {}
              }
            }
          },
          "422": {
            "description": "Validation Error",
            "content": {
              "application/json": {
                "schema": {
                  "$ref": "#/components/schemas/HTTPValidationError"
                }
              }
            }
          }
        }
      }
    },
    "/api/nodes/{node_id}/rdp-config": {
      "post": {
        "summary": "Set Rdp Config",
        "description": "Store RDP host/port for a node and mark it ready.",
        "operationId": "set_rdp_config_api_nodes__node_id__rdp_config_post",
        "parameters": [
          {
            "name": "node_id",
            "in": "path",
            "required": true,
            "schema": {
              "type": "string",
              "title": "Node Id"
            }
          }
        ],
        "requestBody": {
          "required": true,
          "content": {
            "application/json": {
              "schema": {
                "$ref": "#/components/schemas/RdpConfig"
              }
            }
          }
        },
        "responses": {
          "200": {
            "description": "Successful Response",
            "content": {
              "application/json": {
                "schema": {}
              }
            }
          },
          "422": {
            "description": "Validation Error",
            "content": {
              "application/json": {
                "schema": {
                  "$ref": "#/components/schemas/HTTPValidationError"
                }
              }
            }
          }
        }
      }
    },
    "/api/networks/": {
      "get": {
        "summary": "List Networks",
        "operationId": "list_networks_api_networks__get",
        "responses": {
          "200": {
            "description": "Successful Response",
            "content": {
              "application/json": {
                "schema": {}
              }
            }
          }
        }
      }
    },
    "/api/networks/links/{lab_id}": {
      "get": {
        "summary": "List Links",
        "operationId": "list_links_api_networks_links__lab_id__get",
        "parameters": [
          {
            "name": "lab_id",
            "in": "path",
            "required": true,
            "schema": {
              "type": "string",
              "title": "Lab Id"
            }
          }
        ],
        "responses": {
          "200": {
            "description": "Successful Response",
            "content": {
              "application/json": {
                "schema": {}
              }
            }
          },
          "422": {
            "description": "Validation Error",
            "content": {
              "application/json": {
                "schema": {
                  "$ref": "#/components/schemas/HTTPValidationError"
                }
              }
            }
          }
        }
      }
    },
    "/api/networks/links": {
      "post": {
        "summary": "Create Link",
        "operationId": "create_link_api_networks_links_post",
        "requestBody": {
          "content": {
            "application/json": {
              "schema": {
                "$ref": "#/components/schemas/LinkCreate"
              }
            }
          },
          "required": true
        },
        "responses": {
          "201": {
            "description": "Successful Response",
            "content": {
              "application/json": {
                "schema": {}
              }
            }
          },
          "422": {
            "description": "Validation Error",
            "content": {
              "application/json": {
                "schema": {
                  "$ref": "#/components/schemas/HTTPValidationError"
                }
              }
            }
          }
        }
      }
    },
    "/api/networks/links/{link_id}/quality": {
      "patch": {
        "summary": "Set Link Quality",
        "description": "Update quality settings for a link (delay, jitter, loss, bandwidth, style).",
        "operationId": "set_link_quality_api_networks_links__link_id__quality_patch",
        "parameters": [
          {
            "name": "link_id",
            "in": "path",
            "required": true,
            "schema": {
              "type": "string",
              "title": "Link Id"
            }
          }
        ],
        "requestBody": {
          "required": true,
          "content": {
            "application/json": {
              "schema": {
                "$ref": "#/components/schemas/LinkQuality"
              }
            }
          }
        },
        "responses": {
          "200": {
            "description": "Successful Response",
            "content": {
              "application/json": {
                "schema": {}
              }
            }
          },
          "422": {
            "description": "Validation Error",
            "content": {
              "application/json": {
                "schema": {
                  "$ref": "#/components/schemas/HTTPValidationError"
                }
              }
            }
          }
        }
      }
    },
    "/api/networks/links/{link_id}": {
      "delete": {
        "summary": "Delete Link",
        "operationId": "delete_link_api_networks_links__link_id__delete",
        "parameters": [
          {
            "name": "link_id",
            "in": "path",
            "required": true,
            "schema": {
              "type": "string",
              "title": "Link Id"
            }
          }
        ],
        "responses": {
          "204": {
            "description": "Successful Response"
          },
          "422": {
            "description": "Validation Error",
            "content": {
              "application/json": {
                "schema": {
                  "$ref": "#/components/schemas/HTTPValidationError"
                }
              }
            }
          }
        }
      }
    },
    "/api/templates/": {
      "get": {
        "summary": "List Templates",
        "operationId": "list_templates_api_templates__get",
        "parameters": [
          {
            "name": "category",
            "in": "query",
            "required": false,
            "schema": {
              "type": "string",
              "title": "Category"
            }
          }
        ],
        "responses": {
          "200": {
            "description": "Successful Response",
            "content": {
              "application/json": {
                "schema": {}
              }
            }
          },
          "422": {
            "description": "Validation Error",
            "content": {
              "application/json": {
                "schema": {
                  "$ref": "#/components/schemas/HTTPValidationError"
                }
              }
            }
          }
        }
      }
    },
    "/api/templates/categories": {
      "get": {
        "summary": "List Categories",
        "operationId": "list_categories_api_templates_categories_get",
        "responses": {
          "200": {
            "description": "Successful Response",
            "content": {
              "application/json": {
                "schema": {}
              }
            }
          }
        }
      }
    },
    "/api/templates/{template_id}": {
      "get": {
        "summary": "Get Template",
        "operationId": "get_template_api_templates__template_id__get",
        "parameters": [
          {
            "name": "template_id",
            "in": "path",
            "required": true,
            "schema": {
              "type": "string",
              "title": "Template Id"
            }
          }
        ],
        "responses": {
          "200": {
            "description": "Successful Response",
            "content": {
              "application/json": {
                "schema": {}
              }
            }
          },
          "422": {
            "description": "Validation Error",
            "content": {
              "application/json": {
                "schema": {
                  "$ref": "#/components/schemas/HTTPValidationError"
                }
              }
            }
          }
        }
      }
    },
    "/api/templates/{template_id}/deploy": {
      "post": {
        "summary": "Deploy Template",
        "operationId": "deploy_template_api_templates__template_id__deploy_post",
        "parameters": [
          {
            "name": "template_id",
            "in": "path",
            "required": true,
            "schema": {
              "type": "string",
              "title": "Template Id"
            }
          },
          {
            "name": "lab_name",
            "in": "query",
            "required": false,
            "schema": {
              "type": "string",
              "title": "Lab Name"
            }
          }
        ],
        "responses": {
          "200": {
            "description": "Successful Response",
            "content": {
              "application/json": {
                "schema": {}
              }
            }
          },
          "422": {
            "description": "Validation Error",
            "content": {
              "application/json": {
                "schema": {
                  "$ref": "#/components/schemas/HTTPValidationError"
                }
              }
            }
          }
        }
      }
    },
    "/api/updates/check": {
      "get": {
        "tags": [
          "updates"
        ],
        "summary": "Check For Updates",
        "description": "Check for a newer OmniLab version. Honors the configured frequency\nunless force=true. Returns cached result if checked recently.",
        "operationId": "check_for_updates_api_updates_check_get",
        "parameters": [
          {
            "name": "force",
            "in": "query",
            "required": false,
            "schema": {
              "type": "boolean",
              "default": false,
              "title": "Force"
            }
          }
        ],
        "responses": {
          "200": {
            "description": "Successful Response",
            "content": {
              "application/json": {
                "schema": {}
              }
            }
          },
          "422": {
            "description": "Validation Error",
            "content": {
              "application/json": {
                "schema": {
                  "$ref": "#/components/schemas/HTTPValidationError"
                }
              }
            }
          }
        }
      }
    },
    "/api/updates/settings": {
      "get": {
        "tags": [
          "updates"
        ],
        "summary": "Get Update Settings",
        "description": "Get current auto-update check settings.",
        "operationId": "get_update_settings_api_updates_settings_get",
        "responses": {
          "200": {
            "description": "Successful Response",
            "content": {
              "application/json": {
                "schema": {}
              }
            }
          }
        }
      },
      "post": {
        "tags": [
          "updates"
        ],
        "summary": "Update Settings",
        "description": "Change update check preferences.",
        "operationId": "update_settings_api_updates_settings_post",
        "requestBody": {
          "content": {
            "application/json": {
              "schema": {
                "$ref": "#/components/schemas/UpdateSettings"
              }
            }
          },
          "required": true
        },
        "responses": {
          "200": {
            "description": "Successful Response",
            "content": {
              "application/json": {
                "schema": {}
              }
            }
          },
          "422": {
            "description": "Validation Error",
            "content": {
              "application/json": {
                "schema": {
                  "$ref": "#/components/schemas/HTTPValidationError"
                }
              }
            }
          }
        }
      }
    },
    "/api/updates/snooze": {
      "post": {
        "tags": [
          "updates"
        ],
        "summary": "Snooze Version",
        "description": "Hide the update notification for this specific version. User can still\nsee it via System -> Updates, but the corner badge stops nagging.",
        "operationId": "snooze_version_api_updates_snooze_post",
        "requestBody": {
          "content": {
            "application/json": {
              "schema": {
                "$ref": "#/components/schemas/SnoozeRequest"
              }
            }
          },
          "required": true
        },
        "responses": {
          "200": {
            "description": "Successful Response",
            "content": {
              "application/json": {
                "schema": {}
              }
            }
          },
          "422": {
            "description": "Validation Error",
            "content": {
              "application/json": {
                "schema": {
                  "$ref": "#/components/schemas/HTTPValidationError"
                }
              }
            }
          }
        }
      }
    },
    "/api/updates/dismiss": {
      "post": {
        "tags": [
          "updates"
        ],
        "summary": "Dismiss Session",
        "description": "One-session dismissal. The frontend tracks this in sessionStorage,\nso this endpoint is purely a no-op acknowledgment.",
        "operationId": "dismiss_session_api_updates_dismiss_post",
        "responses": {
          "200": {
            "description": "Successful Response",
            "content": {
              "application/json": {
                "schema": {}
              }
            }
          }
        }
      }
    },
    "/api/backup/export": {
      "post": {
        "tags": [
          "backup"
        ],
        "summary": "Export Backup",
        "description": "Create a .omnilab archive of all OmniLab state.",
        "operationId": "export_backup_api_backup_export_post",
        "responses": {
          "200": {
            "description": "Successful Response",
            "content": {
              "application/json": {
                "schema": {}
              }
            }
          }
        }
      }
    },
    "/api/backup/preview": {
      "post": {
        "tags": [
          "backup"
        ],
        "summary": "Preview Backup",
        "description": "Inspect a .omnilab archive without applying it.",
        "operationId": "preview_backup_api_backup_preview_post",
        "requestBody": {
          "content": {
            "multipart/form-data": {
              "schema": {
                "$ref": "#/components/schemas/Body_preview_backup_api_backup_preview_post"
              }
            }
          },
          "required": true
        },
        "responses": {
          "200": {
            "description": "Successful Response",
            "content": {
              "application/json": {
                "schema": {}
              }
            }
          },
          "422": {
            "description": "Validation Error",
            "content": {
              "application/json": {
                "schema": {
                  "$ref": "#/components/schemas/HTTPValidationError"
                }
              }
            }
          }
        }
      }
    },
    "/api/backup/import": {
      "post": {
        "tags": [
          "backup"
        ],
        "summary": "Restore Backup",
        "description": "Restore from a .omnilab archive. Be careful - this can overwrite data.",
        "operationId": "restore_backup_api_backup_import_post",
        "parameters": [
          {
            "name": "overwrite_database",
            "in": "query",
            "required": false,
            "schema": {
              "type": "boolean",
              "default": true,
              "title": "Overwrite Database"
            }
          },
          {
            "name": "overwrite_license",
            "in": "query",
            "required": false,
            "schema": {
              "type": "boolean",
              "default": false,
              "title": "Overwrite License"
            }
          },
          {
            "name": "overwrite_settings",
            "in": "query",
            "required": false,
            "schema": {
              "type": "boolean",
              "default": false,
              "title": "Overwrite Settings"
            }
          }
        ],
        "requestBody": {
          "required": true,
          "content": {
            "multipart/form-data": {
              "schema": {
                "$ref": "#/components/schemas/Body_restore_backup_api_backup_import_post"
              }
            }
          }
        },
        "responses": {
          "200": {
            "description": "Successful Response",
            "content": {
              "application/json": {
                "schema": {}
              }
            }
          },
          "422": {
            "description": "Validation Error",
            "content": {
              "application/json": {
                "schema": {
                  "$ref": "#/components/schemas/HTTPValidationError"
                }
              }
            }
          }
        }
      }
    },
    "/api/health/metrics": {
      "get": {
        "tags": [
          "health"
        ],
        "summary": "Get System Metrics",
        "description": "Combined system + backend process + API health metrics.",
        "operationId": "get_system_metrics_api_health_metrics_get",
        "responses": {
          "200": {
            "description": "Successful Response",
            "content": {
              "application/json": {
                "schema": {}
              }
            }
          }
        }
      }
    },
    "/api/health/docker": {
      "get": {
        "tags": [
          "health"
        ],
        "summary": "Get Docker Info",
        "description": "Docker daemon stats.",
        "operationId": "get_docker_info_api_health_docker_get",
        "responses": {
          "200": {
            "description": "Successful Response",
            "content": {
              "application/json": {
                "schema": {}
              }
            }
          }
        }
      }
    },
    "/api/health/network": {
      "get": {
        "tags": [
          "health"
        ],
        "summary": "Get Network Info",
        "description": "Network: OVS bridges, interfaces.",
        "operationId": "get_network_info_api_health_network_get",
        "responses": {
          "200": {
            "description": "Successful Response",
            "content": {
              "application/json": {
                "schema": {}
              }
            }
          }
        }
      }
    },
    "/api/health/lab-stats": {
      "get": {
        "tags": [
          "health"
        ],
        "summary": "Get Lab Stats",
        "description": "Lab and node statistics from the database.",
        "operationId": "get_lab_stats_api_health_lab_stats_get",
        "responses": {
          "200": {
            "description": "Successful Response",
            "content": {
              "application/json": {
                "schema": {}
              }
            }
          }
        }
      }
    },
    "/api/system/health": {
      "get": {
        "summary": "Health",
        "operationId": "health_api_system_health_get",
        "responses": {
          "200": {
            "description": "Successful Response",
            "content": {
              "application/json": {
                "schema": {}
              }
            }
          }
        }
      }
    },
    "/api/system/info": {
      "get": {
        "summary": "System Info",
        "operationId": "system_info_api_system_info_get",
        "responses": {
          "200": {
            "description": "Successful Response",
            "content": {
              "application/json": {
                "schema": {}
              }
            }
          }
        }
      }
    },
    "/api/system/first-run": {
      "get": {
        "summary": "First Run Status",
        "description": "Whether the install has completed initial setup.",
        "operationId": "first_run_status_api_system_first_run_get",
        "responses": {
          "200": {
            "description": "Successful Response",
            "content": {
              "application/json": {
                "schema": {}
              }
            }
          }
        }
      }
    },
    "/api/system/first-run/complete": {
      "post": {
        "summary": "First Run Complete",
        "description": "Persist the wizard's choices.\n\nIdempotency rule: once `complete` is True we refuse \u2014 see module docstring.",
        "operationId": "first_run_complete_api_system_first_run_complete_post",
        "requestBody": {
          "content": {
            "application/json": {
              "schema": {
                "$ref": "#/components/schemas/FirstRunComplete"
              }
            }
          },
          "required": true
        },
        "responses": {
          "201": {
            "description": "Successful Response",
            "content": {
              "application/json": {
                "schema": {}
              }
            }
          },
          "422": {
            "description": "Validation Error",
            "content": {
              "application/json": {
                "schema": {
                  "$ref": "#/components/schemas/HTTPValidationError"
                }
              }
            }
          }
        }
      }
    },
    "/api/system/email-health": {
      "get": {
        "summary": "Email Health",
        "description": "Provider state for transactional email (Module 8).",
        "operationId": "email_health_api_system_email_health_get",
        "responses": {
          "200": {
            "description": "Successful Response",
            "content": {
              "application/json": {
                "schema": {}
              }
            }
          }
        }
      }
    },
    "/api/console/{node_id}/info": {
      "get": {
        "summary": "Console Info",
        "operationId": "console_info_api_console__node_id__info_get",
        "parameters": [
          {
            "name": "node_id",
            "in": "path",
            "required": true,
            "schema": {
              "type": "string",
              "title": "Node Id"
            }
          }
        ],
        "responses": {
          "200": {
            "description": "Successful Response",
            "content": {
              "application/json": {
                "schema": {}
              }
            }
          },
          "422": {
            "description": "Validation Error",
            "content": {
              "application/json": {
                "schema": {
                  "$ref": "#/components/schemas/HTTPValidationError"
                }
              }
            }
          }
        }
      }
    }
  },
  "components": {
    "schemas": {
      "Body_preview_backup_api_backup_preview_post": {
        "properties": {
          "file": {
            "type": "string",
            "contentMediaType": "application/octet-stream",
            "title": "File"
          }
        },
        "type": "object",
        "required": [
          "file"
        ],
        "title": "Body_preview_backup_api_backup_preview_post"
      },
      "Body_restore_backup_api_backup_import_post": {
        "properties": {
          "file": {
            "type": "string",
            "contentMediaType": "application/octet-stream",
            "title": "File"
          }
        },
        "type": "object",
        "required": [
          "file"
        ],
        "title": "Body_restore_backup_api_backup_import_post"
      },
      "CheckoutSessionRequest": {
        "properties": {
          "plan": {
            "type": "string",
            "title": "Plan"
          },
          "customer_email": {
            "anyOf": [
              {
                "type": "string"
              },
              {
                "type": "null"
              }
            ],
            "title": "Customer Email"
          },
          "promo_code": {
            "anyOf": [
              {
                "type": "string"
              },
              {
                "type": "null"
              }
            ],
            "title": "Promo Code"
          }
        },
        "type": "object",
        "required": [
          "plan"
        ],
        "title": "CheckoutSessionRequest"
      },
      "FirstRunComplete": {
        "properties": {
          "password": {
            "type": "string",
            "minLength": 8,
            "title": "Password"
          },
          "telemetry": {
            "type": "boolean",
            "title": "Telemetry",
            "default": false
          },
          "license_key": {
            "anyOf": [
              {
                "type": "string"
              },
              {
                "type": "null"
              }
            ],
            "title": "License Key"
          }
        },
        "type": "object",
        "required": [
          "password"
        ],
        "title": "FirstRunComplete"
      },
      "HTTPValidationError": {
        "properties": {
          "detail": {
            "items": {
              "$ref": "#/components/schemas/ValidationError"
            },
            "type": "array",
            "title": "Detail"
          }
        },
        "type": "object",
        "title": "HTTPValidationError"
      },
      "ImportPayload": {
        "properties": {
          "schema_version": {
            "type": "integer",
            "title": "Schema Version"
          },
          "product": {
            "anyOf": [
              {
                "type": "string"
              },
              {
                "type": "null"
              }
            ],
            "title": "Product",
            "default": "OmniLab"
          },
          "lab": {
            "additionalProperties": true,
            "type": "object",
            "title": "Lab"
          },
          "nodes": {
            "items": {},
            "type": "array",
            "title": "Nodes",
            "default": []
          },
          "links": {
            "items": {},
            "type": "array",
            "title": "Links",
            "default": []
          }
        },
        "type": "object",
        "required": [
          "schema_version",
          "lab"
        ],
        "title": "ImportPayload"
      },
      "LabCreate": {
        "properties": {
          "name": {
            "type": "string",
            "title": "Name"
          },
          "description": {
            "anyOf": [
              {
                "type": "string"
              },
              {
                "type": "null"
              }
            ],
            "title": "Description",
            "default": ""
          },
          "category": {
            "anyOf": [
              {
                "type": "string"
              },
              {
                "type": "null"
              }
            ],
            "title": "Category",
            "default": "general"
          }
        },
        "type": "object",
        "required": [
          "name"
        ],
        "title": "LabCreate"
      },
      "LicenseActivate": {
        "properties": {
          "key": {
            "type": "string",
            "title": "Key"
          }
        },
        "type": "object",
        "required": [
          "key"
        ],
        "title": "LicenseActivate"
      },
      "LinkCreate": {
        "properties": {
          "lab_id": {
            "type": "string",
            "title": "Lab Id"
          },
          "src_node_id": {
            "type": "string",
            "title": "Src Node Id"
          },
          "dst_node_id": {
            "type": "string",
            "title": "Dst Node Id"
          },
          "style": {
            "anyOf": [
              {
                "type": "string"
              },
              {
                "type": "null"
              }
            ],
            "title": "Style",
            "default": "solid"
          }
        },
        "type": "object",
        "required": [
          "lab_id",
          "src_node_id",
          "dst_node_id"
        ],
        "title": "LinkCreate"
      },
      "LinkQuality": {
        "properties": {
          "delay_ms": {
            "anyOf": [
              {
                "type": "integer"
              },
              {
                "type": "null"
              }
            ],
            "title": "Delay Ms",
            "default": 0
          },
          "jitter_ms": {
            "anyOf": [
              {
                "type": "integer"
              },
              {
                "type": "null"
              }
            ],
            "title": "Jitter Ms",
            "default": 0
          },
          "loss_pct": {
            "anyOf": [
              {
                "type": "number"
              },
              {
                "type": "null"
              }
            ],
            "title": "Loss Pct",
            "default": 0.0
          },
          "bandwidth_kbps": {
            "anyOf": [
              {
                "type": "integer"
              },
              {
                "type": "null"
              }
            ],
            "title": "Bandwidth Kbps",
            "default": 0
          },
          "style": {
            "anyOf": [
              {
                "type": "string"
              },
              {
                "type": "null"
              }
            ],
            "title": "Style"
          }
        },
        "type": "object",
        "title": "LinkQuality"
      },
      "NodeCreate": {
        "properties": {
          "lab_id": {
            "type": "string",
            "title": "Lab Id"
          },
          "name": {
            "type": "string",
            "title": "Name"
          },
          "type": {
            "type": "string",
            "title": "Type"
          },
          "image": {
            "anyOf": [
              {
                "type": "string"
              },
              {
                "type": "null"
              }
            ],
            "title": "Image"
          },
          "x": {
            "anyOf": [
              {
                "type": "number"
              },
              {
                "type": "null"
              }
            ],
            "title": "X",
            "default": 100
          },
          "y": {
            "anyOf": [
              {
                "type": "number"
              },
              {
                "type": "null"
              }
            ],
            "title": "Y",
            "default": 100
          },
          "config": {
            "anyOf": [
              {
                "additionalProperties": true,
                "type": "object"
              },
              {
                "type": "null"
              }
            ],
            "title": "Config",
            "default": {}
          },
          "console_type": {
            "anyOf": [
              {
                "type": "string"
              },
              {
                "type": "null"
              }
            ],
            "title": "Console Type",
            "default": "pty"
          }
        },
        "type": "object",
        "required": [
          "lab_id",
          "name",
          "type"
        ],
        "title": "NodeCreate"
      },
      "NodeUpdate": {
        "properties": {
          "name": {
            "anyOf": [
              {
                "type": "string"
              },
              {
                "type": "null"
              }
            ],
            "title": "Name"
          },
          "config": {
            "anyOf": [
              {
                "type": "string"
              },
              {
                "type": "null"
              }
            ],
            "title": "Config"
          },
          "x": {
            "anyOf": [
              {
                "type": "integer"
              },
              {
                "type": "null"
              }
            ],
            "title": "X"
          },
          "y": {
            "anyOf": [
              {
                "type": "integer"
              },
              {
                "type": "null"
              }
            ],
            "title": "Y"
          }
        },
        "type": "object",
        "title": "NodeUpdate"
      },
      "RdpConfig": {
        "properties": {
          "host": {
            "type": "string",
            "title": "Host"
          },
          "port": {
            "type": "integer",
            "title": "Port",
            "default": 3389
          }
        },
        "type": "object",
        "required": [
          "host"
        ],
        "title": "RdpConfig"
      },
      "SnoozeRequest": {
        "properties": {
          "version": {
            "type": "string",
            "title": "Version"
          }
        },
        "type": "object",
        "required": [
          "version"
        ],
        "title": "SnoozeRequest"
      },
      "UpdateSettings": {
        "properties": {
          "enabled": {
            "anyOf": [
              {
                "type": "boolean"
              },
              {
                "type": "null"
              }
            ],
            "title": "Enabled"
          },
          "frequency_days": {
            "anyOf": [
              {
                "type": "integer"
              },
              {
                "type": "null"
              }
            ],
            "title": "Frequency Days"
          }
        },
        "type": "object",
        "title": "UpdateSettings"
      },
      "ValidationError": {
        "properties": {
          "loc": {
            "items": {
              "anyOf": [
                {
                  "type": "string"
                },
                {
                  "type": "integer"
                }
              ]
            },
            "type": "array",
            "title": "Location"
          },
          "msg": {
            "type": "string",
            "title": "Message"
          },
          "type": {
            "type": "string",
            "title": "Error Type"
          },
          "input": {
            "title": "Input"
          },
          "ctx": {
            "type": "object",
            "title": "Context"
          }
        },
        "type": "object",
        "required": [
          "loc",
          "msg",
          "type"
        ],
        "title": "ValidationError"
      }
    }
  }
}